{"version":"4.1.8","results":[[":src/column-filter.test.ts",{"duration":24.395050000000026,"failed":false}],[":src/grid-theme.test.ts",{"duration":10.153537,"failed":false}],[":src/copy-payloads.test.ts",{"duration":8.455214000000012,"failed":false}],[":src/grid-config.test.ts",{"duration":10.384361999999953,"failed":false}],[":src/sort-util.test.ts",{"duration":11.842160000000007,"failed":false}],[":src/RichGrid.virtual.test.tsx",{"duration":183.36773199999993,"failed":false}],[":src/RichGrid.test.tsx",{"duration":170.5136000000001,"failed":false}],[":src/VirtualGrid.test.tsx",{"duration":116.29335400000002,"failed":false}],[":src/use-hover-expand.test.tsx",{"duration":29.565555000000018,"failed":false}],[":src/use-persisted-column-widths.test.ts",{"duration":19.026895999999965,"failed":false}]]}